Workbook

Sheet Cover
B2: CORPORATE FINANCIAL PLANNING & ANALYSIS
B3: Enterprise Management Reporting, Driver-Based Budgeting & Variance Attribution Model
B5: PORTFOLIO METADATA & MODEL GOVERNANCE
B6: Target Role / Capability | C6: Senior FP&A Analyst / Strategic Finance Manager
B7: Core Competencies Showcased | C7: Driver-Based Budgeting • Rolling Forecasting • PVM Variance • KPI Architecture • Decision Support
B8: Reporting Currency & Scale | C8: INR Crores (₹m synthetic management figures)
B9: Model Cadence & Scope | C9: 24-Month Horizon (FY25-FY26), 3 Business Units (Consumer, Enterprise, Digital)
B10: Audit & Standard Compliance | C10: FAST Standard-aligned, Zero Hardcoded Totals, Dynamic SUMIFS Aggregations
B11: Last Updated / Verified | C11: Q3 2026 (Reflects 8+4 Rolling Run-Rate)
B13: MODEL DIRECTORY & TABLE OF CONTENTS
B14: Sheet Name | C14: Tab Hyperlink | D14: Functional Purpose & Employer Takeaway
B15: Executive Dashboard | C15: =HYPERLINK("#Dashboard!A1", "Jump to Dashboard →") -> Jump to Dashboard → | D15: Consolidated KPI scoreboard, segment profitability, and executive trend charts
B16: Monthly Variance Report | C16: =HYPERLINK("#Monthly_Report!A1", "Jump to Monthly_Report →") -> Jump to Monthly_Report → | D16: Dynamic 24-month Actual vs Budget vs Forecast revenue & operating profit bridge
B17: Variance Driver Analysis | C17: =HYPERLINK("#Driver_Analysis!A1", "Jump to Driver_Analysis →") -> Jump to Driver_Analysis → | D17: P&L bridge decomposing variance into Volume/Mix, Gross Margin, and Controllable Opex
B18: KPI Driver Tree | C18: =HYPERLINK("#KPI_Tree!A1", "Jump to KPI_Tree →") -> Jump to KPI_Tree → | D18: Operational driver decomposition linking conversion, gross margin, and overheads to ROIC
B19: Assumptions & Scenarios | C19: =HYPERLINK("#Assumptions!A1", "Jump to Assumptions →") -> Jump to Assumptions → | D19: Dynamic macro scenario switcher (Downside / Base / Upside) and operating ratios
B20: Integrity & Audit Checks | C20: =HYPERLINK("#Checks!A1", "Jump to Checks →") -> Jump to Checks → | D20: Automated reconciliation tying out report totals, balance tolerance, and raw data integrity
B21: Normalized Raw Data | C21: =HYPERLINK("#Data_Raw!A1", "Jump to Data_Raw →") -> Jump to Data_Raw → | D21: Granular transactional fact table (72 records) feeding dynamic multi-criteria aggregations

Sheet Data_Raw
A1: Month | B1: Year | C1: MonthNo | D1: Segment | E1: Revenue | F1: COGS | G1: GrossProfit | H1: Headcount | I1: Payroll | J1: Marketing | K1: Technology | L1: OtherOpex | M1: Capex | N1: Volume | O1: BudgetRevenue | P1: BudgetGrossMargin | Q1: BudgetCOGS | R1: BudgetPayroll | S1: BudgetMarketing | T1: BudgetTechnology | U1: BudgetOtherOpex | V1: BudgetCapex | W1: Status | X1: ForecastRevenue | Y1: ForecastCOGS | Z1: ForecastPayroll | AA1: ForecastMarketing | AB1: ForecastTechnology | AC1: ForecastOtherOpex | AD1: ForecastCapex | AE1: EBIT | AF1: BudgetGrossProfit | AG1: BudgetEBIT | AH1: ForecastGrossProfit | AI1: ForecastEBIT
A2: 45658 | B2: 2025 | C2: 1 | D2: Consumer | E2: 492.94281 | F2: 327.43388 | G2: 165.50893 | H2: 180 | I2: 1.53 | J2: 22.182427 | K2: 8.8729706 | L2: 17.252998 | M2: 5.9153137 | N2: 4.9294281 | O2: 493.12375 | P2: 0.345 | Q2: 322.99606 | R2: 1.5606 | S2: 22.683693 | T2: 9.3693513 | U2: 16.766208 | V2: 6.4106088 | W2: Actual | X2: 492.94281 | Y2: 327.43388 | Z2: 1.53 | AA2: 22.182427 | AB2: 8.8729706 | AC2: 17.252998 | AD2: 5.9153137 | AE2: 115.67054 | AF2: 170.12769 | AG2: 119.74784 | AH2: 165.50893 | AI2: 115.67054
A3: 45658 | B3: 2025 | C3: 1 | D3: Enterprise | E3: 287.53518 | F3: 168.31517 | G3: 119.22002 | H3: 105 | I3: 0.8925 | J3: 8.0509851 | K3: 7.1883796 | L3: 10.063731 | M3: 3.4504222 | N3: 2.8753518 | O3: 289.69847 | P3: 0.415 | Q3: 169.47361 | R3: 0.91035 | S3: 8.6909542 | T3: 6.9527634 | U3: 9.8497481 | V3: 3.7660802 | W3: Actual | X3: 287.53518 | Y3: 168.31517 | Z3: 0.8925 | AA3: 8.0509851 | AB3: 7.1883796 | AC3: 10.063731 | AD3: 3.4504222 | AE3: 93.024421 | AF3: 120.22487 | AG3: 93.821051 | AH3: 119.22002 | AI3: 93.024421
A4: 45658 | B4: 2025 | C4: 1 | D4: Digital | E4: 161.0841 | F4: 69.115253 | G4: 91.968844 | H4: 75 | I4: 0.75 | J4: 9.6650458 | K4: 8.0542049 | L4: 5.6379434 | M4: 2.8995138 | N4: 1.5341343 | O4: 161.72558 | P4: 0.59 | Q4: 66.307486 | R4: 0.765 | S4: 9.3800834 | T4: 7.7628276 | U4: 5.4986696 | V4: 3.2345115 | W4: Actual | X4: 161.0841 | Y4: 69.115253 | Z4: 0.75 | AA4: 9.6650458 | AB4: 8.0542049 | AC4: 5.6379434 | AD4: 2.8995138 | AE4: 67.86165 | AF4: 95.41809 | AG4: 72.011509 | AH4: 91.968844 | AI4: 67.86165
A5: 45689 | B5: 2025 | C5: 2 | D5: Consumer | E5: 480.55497 | F5: 317.78632 | G5: 162.76864 | H5: 180 | I5: 1.53 | J5: 21.624973 | K5: 8.6499894 | L5: 16.819424 | M5: 5.7666596 | N5: 4.8055497 | O5: 486.54545 | P5: 0.345 | Q5: 318.68727 | R5: 1.5606 | S5: 22.381091 | T5: 9.2443636 | U5: 16.542545 | V5: 6.3250909 | W5: Actual | X5: 480.55497 | Y5: 317.78632 | Z5: 1.53 | AA5: 21.624973 | AB5: 8.6499894 | AC5: 16.819424 | AD5: 5.7666596 | AE5: 114.14426 | AF5: 167.85818 | AG5: 118.12958 | AH5: 162.76864 | AI5: 114.14426
A6: 45689 | B6: 2025 | C6: 2 | D6: Enterprise | E6: 276.24392 | F6: 164.1433 | G6: 112.10062 | H6: 105 | I6: 0.8925 | J6: 7.7348298 | K6: 6.906098 | L6: 9.6685372 | M6: 3.314927 | N6: 2.7624392 | O6: 285.68805 | P6: 0.415 | Q6: 167.12751 | R6: 0.91035 | S6: 8.5706415 | T6: 6.8565132 | U6: 9.7133937 | V6: 3.7139446 | W6: Actual | X6: 276.24392 | Y6: 164.1433 | Z6: 0.8925 | AA6: 7.7348298 | AB6: 6.906098 | AC6: 9.6685372 | AD6: 3.314927 | AE6: 86.898653 | AF6: 118.56054 | AG6: 92.509642 | AH6: 112.10062 | AI6: 86.898653
A7: 45689 | B7: 2025 | C7: 2 | D7: Digital | E7: 169.46146 | F7: 70.256444 | G7: 99.205013 | H7: 75 | I7: 0.75 | J7: 10.167687 | K7: 8.4730728 | L7: 5.931151 | M7: 3.0503062 | N7: 1.6139186 | O7: 172.48242 | P7: 0.59 | Q7: 70.717794 | R7: 0.765 | S7: 10.003981 | T7: 8.2791564 | U7: 5.8644024 | V7: 3.4496485 | W7: Actual | X7: 169.46146 | Y7: 70.256444 | Z7: 0.75 | AA7: 10.167687 | AB7: 8.4730728 | AC7: 5.931151 | AD7: 3.0503062 | AE7: 73.883102 | AF7: 101.76463 | AG7: 76.852091 | AH7: 99.205013 | AI7: 73.883102
A8: 45717 | B8: 2025 | C8: 3 | D8: Consumer | E8: 510.44123 | F8: 334.54362 | G8: 175.89761 | H8: 180 | I8: 1.53 | J8: 22.969855 | K8: 9.1879422 | L8: 17.865443 | M8: 6.1252948 | N8: 5.1044123 | O8: 516.64032 | P8: 0.345 | Q8: 338.39941 | R8: 1.5606 | S8: 23.765455 | T8: 9.8161661 | U8: 17.565771 | V8: 6.7163242 | W8: Actual | X8: 510.44123 | Y8: 334.54362 | Z8: 1.53 | AA8: 22.969855 | AB8: 9.1879422 | AC8: 17.865443 | AD8: 6.1252948 | AE8: 124.34437 | AF8: 178.24091 | AG8: 125.53292 | AH8: 175.89761 | AI8: 124.34437
A9: 45717 | B9: 2025 | C9: 3 | D9: Enterprise | E9: 297.43619 | F9: 176.74483 | G9: 120.69136 | H9: 105 | I9: 0.8925 | J9: 8.3282134 | K9: 7.4359048 | L9: 10.410267 | M9: 3.5692343 | N9: 2.9743619 | O9: 296.353 | P9: 0.415 | Q9: 173.36651 | R9: 0.91035 | S9: 8.89059 | T9: 7.112472 | U9: 10.076002 | V9: 3.852589 | W9: Actual | X9: 297.43619 | Y9: 176.74483 | Z9: 0.8925 | AA9: 8.3282134 | AB9: 7.4359048 | AC9: 10.410267 | AD9: 3.5692343 | AE9: 93.624478 | AF9: 122.9865 | AG9: 95.997081 | AH9: 120.69136 | AI9: 93.624478
A10: 45717 | B10: 2025 | C10: 3 | D10: Digital | E10: 178.02619 | F10: 75.959115 | G10: 102.06708 | H10: 75 | I10: 0.75 | J10: 10.681571 | K10: 8.9013095 | L10: 6.2309167 | M10: 3.2044714 | N10: 1.6954875 | O10: 175.33011 | P10: 0.59 | Q10: 71.885345 | R10: 0.765 | S10: 10.169146 | T10: 8.4158453 | U10: 5.9612237 | V10: 3.5066022 | W10: Actual | X10: 178.02619 | Y10: 75.959115 | Z10: 0.75 | AA10: 10.681571 | AB10: 8.9013095 | AC10: 6.2309167 | AD10: 3.2044714 | AE10: 75.503278 | AF10: 103.44476 | AG10: 78.13355 | AH10: 102.06708 | AI10: 75.503278
A11: 45748 | B11: 2025 | C11: 4 | D11: Consumer | E11: 531.20729 | F11: 350.70501 | G11: 180.50227 | H11: 180 | I11: 1.53 | J11: 23.904328 | K11: 9.5617311 | L11: 18.592255 | M11: 6.3744874 | N11: 5.3120729 | O11: 534.52545 | P11: 0.345 | Q11: 350.11417 | R11: 1.5606 | S11: 24.588171 | T11: 10.155984 | U11: 18.173865 | V11: 6.9488308 | W11: Actual | X11: 531.20729 | Y11: 350.70501 | Z11: 1.53 | AA11: 23.904328 | AB11: 9.5617311 | AC11: 18.592255 | AD11: 6.3744874 | AE11: 126.91396 | AF11: 184.41128 | AG11: 129.93266 | AH11: 180.50227 | AI11: 126.91396
A12: 45748 | B12: 2025 | C12: 4 | D12: Enterprise | E12: 298.49409 | F12: 177.11152 | G12: 121.38257 | H12: 105 | I12: 0.8925 | J12: 8.3578344 | K12: 7.4623522 | L12: 10.447293 | M12: 3.581929 | N12: 2.9849409 | O12: 302.68253 | P12: 0.415 | Q12: 177.06928 | R12: 0.91035 | S12: 9.0804759 | T12: 7.2643807 | U12: 10.291206 | V12: 3.9348729 | W12: Actual | X12: 298.49409 | Y12: 177.11152 | Z12: 0.8925 | AA12: 8.3578344 | AB12: 7.4623522 | AC12: 10.447293 | AD12: 3.581929 | AE12: 94.222589 | AF12: 125.61325 | AG12: 98.066837 | AH12: 121.38257 | AI12: 94.222589
A13: 45748 | B13: 2025 | C13: 4 | D13: Digital | E13: 185.42724 | F13: 78.078871 | G13: 107.34836 | H13: 75 | I13: 0.75 | J13: 11.125634 | K13: 9.2713618 | L13: 6.4899532 | M13: 3.3376902 | N13: 1.7659737 | O13: 194.10945 | P13: 0.59 | Q13: 79.584873 | R13: 0.765 | S13: 11.258348 | T13: 9.3172534 | U13: 6.5997212 | V13: 3.8821889 | W13: Actual | X13: 185.42724 | Y13: 78.078871 | Z13: 0.75 | AA13: 11.125634 | AB13: 9.2713618 | AC13: 6.4899532 | AD13: 3.3376902 | AE13: 79.711416 | AF13: 114.52457 | AG13: 86.584251 | AH13: 107.34836 | AI13: 79.711416
... A73: 46357 | B73: 2026 | C73: 12 | D73: Digital | E73: 270.9678 | F73: 113.30159 | G73: 157.66621 | H73: 83 | I73: 0.8632 | J73: 16.258068 | K73: 13.54839 | L73: 9.4838732 | M73: 4.8774205 | N73: 2.5806458 | O73: 283.17257 | P73: 0.59 | Q73: 116.10075 | R73: 0.88478 | S73: 16.424009 | T73: 13.592283 | U73: 9.6278672 | V73: 5.6634513 | W73: Forecast | X73: 283.17257 | Y73: 116.10075 | Z73: 0.88478 | AA73: 16.424009 | AB73: 13.592283 | AC73: 9.6278672 | AD73: 5.6634513 | AE73: 117.51268 | AF73: 167.07181 | AG73: 126.54287 | AH73: 167.07181 | AI73: 126.54287

Sheet Assumptions
B2: FP&A Planning Assumptions & Scenario Control Panel | I2: INTEGRITY AUDIT
B3: Dynamic macro scenario selector and operational planning levers. | I3: =IF(Checks!$C$13="ALL CHECKS PASS", "🟢 ALL CHECKS PASS", "🔴 AUDIT WARNING") -> 🟢 ALL CHECKS PASS
B5: SCENARIO CONTROL SWITCH
B6: Active Scenario ID (1=Downside, 2=Base, 3=Upside): | E6: 2 | F6: =CHOOSE(E6, "DOWNSIDE CASE", "BASE BUDGET", "UPSIDE CASE") -> BASE BUDGET
B8: Planning Lever | C8: Downside (1) | D8: Base (2) | E8: Upside (3) | F8: Active Value | G8: Unit | H8: Strategic Context
B9: Consumer Target Gross Margin | C9: 0.325 | D9: 0.345 | E9: 0.365 | F9: =INDEX(C9:E9, 1, $E$6) -> 0.345 | G9: % | H9: Retail product pricing & commodity COGS sensitivity
B10: Enterprise Target Gross Margin | C10: 0.395 | D10: 0.415 | E10: 0.435 | F10: =INDEX(C10:E10, 1, $E$6) -> 0.415 | G10: % | H10: B2B long-term contract pricing & SLA delivery costs
B11: Digital Target Gross Margin | C11: 0.56 | D11: 0.59 | E11: 0.62 | F11: =INDEX(C11:E11, 1, $E$6) -> 0.59 | G11: % | H11: High operating-leverage platform subscription revenue
B12: Headcount Expansion Cap | C12: 0.06 | D12: 0.04 | E12: 0.025 | F12: =INDEX(C12:E12, 1, $E$6) -> 0.04 | G12: % | H12: Annual net-new organizational headcount constraint
B13: Salary Cost Inflation | C13: 0.04 | D13: 0.025 | E13: 0.02 | F13: =INDEX(C13:E13, 1, $E$6) -> 0.025 | G13: % | H13: Merit cycle adjustments & statutory inflation impact
B14: Target Marketing % Revenue | C14: 0.05 | D14: 0.046 | E14: 0.043 | F14: =INDEX(C14:E14, 1, $E$6) -> 0.046 | G14: % | H14: Discretionary growth CAC investment ratio
B15: Target Technology % Revenue | C15: 0.025 | D15: 0.022 | E15: 0.02 | F15: =INDEX(C15:E15, 1, $E$6) -> 0.022 | G15: % | H15: Core Cloud, ERP and security infrastructure baseline
B16: Capex % Revenue | C16: 0.015 | D16: 0.013 | E16: 0.01 | F16: =INDEX(C16:E16, 1, $E$6) -> 0.013 | G16: % | H16: Maintenance and growth capital expenditures
B19: Forecast Cutoff Date: | C19: 2026-08-01 | D19: Separates closed historical actuals from 8+4 rolling run-rate forecast

Sheet Monthly_Report
B2: Monthly Actual vs Budget Performance Statement | I2: INTEGRITY AUDIT
B3: Multi-condition SUMIFS aggregation across FY25-FY26 with dynamic variance attribution (₹m). | I3: =IF(Checks!$C$13="ALL CHECKS PASS", "🟢 ALL CHECKS PASS", "🔴 AUDIT WARNING") -> 🟢 ALL CHECKS PASS
B5: Month | C5: Status | D5: Actual Rev | E5: Budget Rev | F5: Rev Var ($) | G5: Rev Var (%) | H5: Actual EBIT | I5: Budget EBIT | J5: EBIT Var ($) | K5: EBIT Var (%) | L5: EBIT Margin | M5: Variance Flag
B6: 45658 | C6: =IF(B6<=Assumptions!$C$19, "Actual", "Forecast") -> Actual | D6: =SUMIFS(Data_Raw!$E$2:$E$73, Data_Raw!$A$2:$A$73, B6) -> 941.56209 | E6: =SUMIFS(Data_Raw!$O$2:$O$73, Data_Raw!$A$2:$A$73, B6) -> 944.5478 | F6: =D6-E6 -> -2.985709 | G6: =IF(E6=0, 0, F6/E6) -> -0.003160993 | H6: =SUMIFS(Data_Raw!$AE$2:$AE$73, Data_Raw!$A$2:$A$73, B6) -> 276.55661 | I6: =SUMIFS(Data_Raw!$AG$2:$AG$73, Data_Raw!$A$2:$A$73, B6) -> 285.5804 | J6: =H6-I6 -> -9.023795 | K6: =IF(I6=0, 0, J6/ABS(I6)) -> -0.031598089 | L6: =IF(D6=0, 0, H6/D6) -> 0.29372105 | M6: =IF(K6<-0.05, "⚠️ REVIEW", IF(K6>0.05, "⭐ FAVORABLE", "ON TRACK")) -> ON TRACK
B7: 45689 | C7: =IF(B7<=Assumptions!$C$19, "Actual", "Forecast") -> Actual | D7: =SUMIFS(Data_Raw!$E$2:$E$73, Data_Raw!$A$2:$A$73, B7) -> 926.26034 | E7: =SUMIFS(Data_Raw!$O$2:$O$73, Data_Raw!$A$2:$A$73, B7) -> 944.71592 | F7: =D7-E7 -> -18.455582 | G7: =IF(E7=0, 0, F7/E7) -> -0.019535589 | H7: =SUMIFS(Data_Raw!$AE$2:$AE$73, Data_Raw!$A$2:$A$73, B7) -> 274.92601 | I7: =SUMIFS(Data_Raw!$AG$2:$AG$73, Data_Raw!$A$2:$A$73, B7) -> 287.49131 | J7: =H7-I7 -> -12.565303 | K7: =IF(I7=0, 0, J7/ABS(I7)) -> -0.043706722 | L7: =IF(D7=0, 0, H7/D7) -> 0.29681289 | M7: =IF(K7<-0.05, "⚠️ REVIEW", IF(K7>0.05, "⭐ FAVORABLE", "ON TRACK")) -> ON TRACK
B8: 45717 | C8: =IF(B8<=Assumptions!$C$19, "Actual", "Forecast") -> Actual | D8: =SUMIFS(Data_Raw!$E$2:$E$73, Data_Raw!$A$2:$A$73, B8) -> 985.90362 | E8: =SUMIFS(Data_Raw!$O$2:$O$73, Data_Raw!$A$2:$A$73, B8) -> 988.32343 | F8: =D8-E8 -> -2.4198165 | G8: =IF(E8=0, 0, F8/E8) -> -0.0024484055 | H8: =SUMIFS(Data_Raw!$AE$2:$AE$73, Data_Raw!$A$2:$A$73, B8) -> 293.47213 | I8: =SUMIFS(Data_Raw!$AG$2:$AG$73, Data_Raw!$A$2:$A$73, B8) -> 299.66355 | J8: =H8-I8 -> -6.1914236 | K8: =IF(I8=0, 0, J8/ABS(I8)) -> -0.02066125 | L8: =IF(D8=0, 0, H8/D8) -> 0.29766817 | M8: =IF(K8<-0.05, "⚠️ REVIEW", IF(K8>0.05, "⭐ FAVORABLE", "ON TRACK")) -> ON TRACK
B9: 45748 | C9: =IF(B9<=Assumptions!$C$19, "Actual", "Forecast") -> Actual | D9: =SUMIFS(Data_Raw!$E$2:$E$73, Data_Raw!$A$2:$A$73, B9) -> 1015.1286 | E9: =SUMIFS(Data_Raw!$O$2:$O$73, Data_Raw!$A$2:$A$73, B9) -> 1031.3174 | F9: =D9-E9 -> -16.188818 | G9: =IF(E9=0, 0, F9/E9) -> -0.015697222 | H9: =SUMIFS(Data_Raw!$AE$2:$AE$73, Data_Raw!$A$2:$A$73, B9) -> 300.84796 | I9: =SUMIFS(Data_Raw!$AG$2:$AG$73, Data_Raw!$A$2:$A$73, B9) -> 314.58375 | J9: =H9-I9 -> -13.735787 | K9: =IF(I9=0, 0, J9/ABS(I9)) -> -0.04366337 | L9: =IF(D9=0, 0, H9/D9) -> 0.29636438 | M9: =IF(K9<-0.05, "⚠️ REVIEW", IF(K9>0.05, "⭐ FAVORABLE", "ON TRACK")) -> ON TRACK
B10: 45778 | C10: =IF(B10<=Assumptions!$C$19, "Actual", "Forecast") -> Actual | D10: =SUMIFS(Data_Raw!$E$2:$E$73, Data_Raw!$A$2:$A$73, B10) -> 1009.684 | E10: =SUMIFS(Data_Raw!$O$2:$O$73, Data_Raw!$A$2:$A$73, B10) -> 1029.8251 | F10: =D10-E10 -> -20.141101 | G10: =IF(E10=0, 0, F10/E10) -> -0.019557788 | H10: =SUMIFS(Data_Raw!$AE$2:$AE$73, Data_Raw!$A$2:$A$73, B10) -> 301.5035 | I10: =SUMIFS(Data_Raw!$AG$2:$AG$73, Data_Raw!$A$2:$A$73, B10) -> 313.44113 | J10: =H10-I10 -> -11.937624 | K10: =IF(I10=0, 0, J10/ABS(I10)) -> -0.038085698 | L10: =IF(D10=0, 0, H10/D10) -> 0.29861175 | M10: =IF(K10<-0.05, "⚠️ REVIEW", IF(K10>0.05, "⭐ FAVORABLE", "ON TRACK")) -> ON TRACK
B11: 45809 | C11: =IF(B11<=Assumptions!$C$19, "Actual", "Forecast") -> Actual | D11: =SUMIFS(Data_Raw!$E$2:$E$73, Data_Raw!$A$2:$A$73, B11) -> 1056.5479 | E11: =SUMIFS(Data_Raw!$O$2:$O$73, Data_Raw!$A$2:$A$73, B11) -> 1052.6231 | F11: =D11-E11 -> 3.9247475 | G11: =IF(E11=0, 0, F11/E11) -> 0.00372854 | H11: =SUMIFS(Data_Raw!$AE$2:$AE$73, Data_Raw!$A$2:$A$73, B11) -> 312.51269 | I11: =SUMIFS(Data_Raw!$AG$2:$AG$73, Data_Raw!$A$2:$A$73, B11) -> 318.77668 | J11: =H11-I11 -> -6.2639884 | K11: =IF(I11=0, 0, J11/ABS(I11)) -> -0.019650083 | L11: =IF(D11=0, 0, H11/D11) -> 0.29578659 | M11: =IF(K11<-0.05, "⚠️ REVIEW", IF(K11>0.05, "⭐ FAVORABLE", "ON TRACK")) -> ON TRACK
B12: 45839 | C12: =IF(B12<=Assumptions!$C$19, "Actual", "Forecast") -> Actual | D12: =SUMIFS(Data_Raw!$E$2:$E$73, Data_Raw!$A$2:$A$73, B12) -> 975.76612 | E12: =SUMIFS(Data_Raw!$O$2:$O$73, Data_Raw!$A$2:$A$73, B12) -> 1008.3257 | F12: =D12-E12 -> -32.55956 | G12: =IF(E12=0, 0, F12/E12) -> -0.032290718 | H12: =SUMIFS(Data_Raw!$AE$2:$AE$73, Data_Raw!$A$2:$A$73, B12) -> 290.53498 | I12: =SUMIFS(Data_Raw!$AG$2:$AG$73, Data_Raw!$A$2:$A$73, B12) -> 305.89762 | J12: =H12-I12 -> -15.362639 | K12: =IF(I12=0, 0, J12/ABS(I12)) -> -0.050221507 | L12: =IF(D12=0, 0, H12/D12) -> 0.29775063 | M12: =IF(K12<-0.05, "⚠️ REVIEW", IF(K12>0.05, "⭐ FAVORABLE", "ON TRACK")) -> ⚠️ REVIEW
B13: 45870 | C13: =IF(B13<=Assumptions!$C$19, "Actual", "Forecast") -> Actual | D13: =SUMIFS(Data_Raw!$E$2:$E$73, Data_Raw!$A$2:$A$73, B13) -> 985.98427 | E13: =SUMIFS(Data_Raw!$O$2:$O$73, Data_Raw!$A$2:$A$73, B13) -> 998.80314 | F13: =D13-E13 -> -12.81887 | G13: =IF(E13=0, 0, F13/E13) -> -0.012834231 | H13: =SUMIFS(Data_Raw!$AE$2:$AE$73, Data_Raw!$A$2:$A$73, B13) -> 295.4781 | I13: =SUMIFS(Data_Raw!$AG$2:$AG$73, Data_Raw!$A$2:$A$73, B13) -> 305.30991 | J13: =H13-I13 -> -9.8318019 | K13: =IF(I13=0, 0, J13/ABS(I13)) -> -0.032202695 | L13: =IF(D13=0, 0, H13/D13) -> 0.29967831 | M13: =IF(K13<-0.05, "⚠️ REVIEW", IF(K13>0.05, "⭐ FAVORABLE", "ON TRACK")) -> ON TRACK
B14: 45901 | C14: =IF(B14<=Assumptions!$C$19, "Actual", "Forecast") -> Actual | D14: =SUMIFS(Data_Raw!$E$2:$E$73, Data_Raw!$A$2:$A$73, B14) -> 1023.7223 | E14: =SUMIFS(Data_Raw!$O$2:$O$73, Data_Raw!$A$2:$A$73, B14) -> 1035.249 | F14: =D14-E14 -> -11.526749 | G14: =IF(E14=0, 0, F14/E14) -> -0.011134277 | H14: =SUMIFS(Data_Raw!$AE$2:$AE$73, Data_Raw!$A$2:$A$73, B14) -> 304.0349 | I14: =SUMIFS(Data_Raw!$AG$2:$AG$73, Data_Raw!$A$2:$A$73, B14) -> 312.91433 | J14: =H14-I14 -> -8.8794268 | K14: =IF(I14=0, 0, J14/ABS(I14)) -> -0.028376543 | L14: =IF(D14=0, 0, H14/D14) -> 0.29698963 | M14: =IF(K14<-0.05, "⚠️ REVIEW", IF(K14>0.05, "⭐ FAVORABLE", "ON TRACK")) -> ON TRACK
B15: 45931 | C15: =IF(B15<=Assumptions!$C$19, "Actual", "Forecast") -> Actual | D15: =SUMIFS(Data_Raw!$E$2:$E$73, Data_Raw!$A$2:$A$73, B15) -> 1045.6202 | E15: =SUMIFS(Data_Raw!$O$2:$O$73, Data_Raw!$A$2:$A$73, B15) -> 1058.9772 | F15: =D15-E15 -> -13.357007 | G15: =IF(E15=0, 0, F15/E15) -> -0.012613121 | H15: =SUMIFS(Data_Raw!$AE$2:$AE$73, Data_Raw!$A$2:$A$73, B15) -> 313.2251 | I15: =SUMIFS(Data_Raw!$AG$2:$AG$73, Data_Raw!$A$2:$A$73, B15) -> 320.74332 | J15: =H15-I15 -> -7.5182225 | K15: =IF(I15=0, 0, J15/ABS(I15)) -> -0.023439997 | L15: =IF(D15=0, 0, H15/D15) -> 0.29955915 | M15: =IF(K15<-0.05, "⚠️ REVIEW", IF(K15>0.05, "⭐ FAVORABLE", "ON TRACK")) -> ON TRACK
B16: 45962 | C16: =IF(B16<=Assumptions!$C$19, "Actual", "Forecast") -> Actual | D16: =SUMIFS(Data_Raw!$E$2:$E$73, Data_Raw!$A$2:$A$73, B16) -> 1078.4401 | E16: =SUMIFS(Data_Raw!$O$2:$O$73, Data_Raw!$A$2:$A$73, B16) -> 1088.7827 | F16: =D16-E16 -> -10.342571 | G16: =IF(E16=0, 0, F16/E16) -> -0.0094992055 | H16: =SUMIFS(Data_Raw!$AE$2:$AE$73, Data_Raw!$A$2:$A$73, B16) -> 324.38507 | I16: =SUMIFS(Data_Raw!$AG$2:$AG$73, Data_Raw!$A$2:$A$73, B16) -> 334.67146 | J16: =H16-I16 -> -10.286391 | K16: =IF(I16=0, 0, J16/ABS(I16)) -> -0.030735789 | L16: =IF(D16=0, 0, H16/D16) -> 0.30079098 | M16: =IF(K16<-0.05, "⚠️ REVIEW", IF(K16>0.05, "⭐ FAVORABLE", "ON TRACK")) -> ON TRACK
B17: 45992 | C17: =IF(B17<=Assumptions!$C$19, "Actual", "Forecast") -> Actual | D17: =SUMIFS(Data_Raw!$E$2:$E$73, Data_Raw!$A$2:$A$73, B17) -> 1171.4851 | E17: =SUMIFS(Data_Raw!$O$2:$O$73, Data_Raw!$A$2:$A$73, B17) -> 1191.0879 | F17: =D17-E17 -> -19.602781 | G17: =IF(E17=0, 0, F17/E17) -> -0.01645788 | H17: =SUMIFS(Data_Raw!$AE$2:$AE$73, Data_Raw!$A$2:$A$73, B17) -> 345.60848 | I17: =SUMIFS(Data_Raw!$AG$2:$AG$73, Data_Raw!$A$2:$A$73, B17) -> 361.98463 | J17: =H17-I17 -> -16.376151 | K17: =IF(I17=0, 0, J17/ABS(I17)) -> -0.045239906 | L17: =IF(D17=0, 0, H17/D17) -> 0.29501739 | M17: =IF(K17<-0.05, "⚠️ REVIEW", IF(K17>0.05, "⭐ FAVORABLE", "ON TRACK")) -> ON TRACK
... B29: 46357 | C29: =IF(B29<=Assumptions!$C$19, "Actual", "Forecast") -> Actual | D29: =SUMIFS(Data_Raw!$E$2:$E$73, Data_Raw!$A$2:$A$73, B29) -> 1511.5737 | E29: =SUMIFS(Data_Raw!$O$2:$O$73, Data_Raw!$A$2:$A$73, B29) -> 1553.051 | F29: =D29-E29 -> -41.477294 | G29: =IF(E29=0, 0, F29/E29) -> -0.026706974 | H29: =SUMIFS(Data_Raw!$AE$2:$AE$73, Data_Raw!$A$2:$A$73, B29) -> 458.50119 | I29: =SUMIFS(Data_Raw!$AG$2:$AG$73, Data_Raw!$A$2:$A$73, B29) -> 473.85143 | J29: =H29-I29 -> -15.350238 | K29: =IF(I29=0, 0, J29/ABS(I29)) -> -0.032394621 | L29: =IF(D29=0, 0, H29/D29) -> 0.30332704 | M29: =IF(K29<-0.05, "⚠️ REVIEW", IF(K29>0.05, "⭐ FAVORABLE", "ON TRACK")) -> ON TRACK
B30: Consolidated Total | D30: =SUM(D6:D29) -> 27609.673 | E30: =SUM(E6:E29) -> 28238.293 | F30: =D30-E30 -> -628.61985 | G30: =F30/E30 -> -0.022261255 | H30: =SUM(H6:H29) -> 8248.2817 | I30: =SUM(I6:I29) -> 8625.854 | J30: =H30-I30 -> -377.57233 | K30: =J30/ABS(I30) -> -0.043772168 | L30: =H30/D30 -> 0.29874608 | M30: =IF(K30<-0.05, "⚠️ REVIEW", "ON TRACK") -> ON TRACK

Sheet Driver_Analysis
B2: Management Variance Bridge & Profitability Decomposition | I2: INTEGRITY AUDIT
B3: Systematic attribution bridging Budget EBIT to Reconciled Actual EBIT (₹m). | I3: =IF(Checks!$C$13="ALL CHECKS PASS", "🟢 ALL CHECKS PASS", "🔴 AUDIT WARNING") -> 🟢 ALL CHECKS PASS
B5: P&L LINE-ITEM ATTRIBUTION BRIDGE
B6: Attribution Step / Driver | C6: Budget Baseline | D6: Impact (₹m) | E6: Cumulative Bridge | F6: Variance Category | G6: Root Cause & Strategic Narrative
B7: Base Budget EBIT Target | C7: =Monthly_Report!I30 -> 8625.854 | D7: 0 | E7: =C7 -> 8625.854 | F7: Baseline | G7: Full-year planned operating target approved by board
B8: Revenue Volume / Demand Variance | C8: 0 | D8: =Monthly_Report!F30 -> -628.61985 | E8: =E7+D8 -> 7997.2341 | F8: Top-line | G8: Macro market demand softness and Enterprise contract slip
B9: Gross Margin / COGS Impact | C9: 0 | D9: =(SUM(Data_Raw!$G$2:$G$73)-SUM(Data_Raw!$AF$2:$AF$73)) - Monthly_Report!F30 -> 195.86545 | E9: =E8+D9 -> 8193.0996 | F9: COGS | G9: Input cost inflation in Consumer partially mitigated by Digital mix
B10: Payroll & Comp Optimization | C10: 0 | D10: =SUM(Data_Raw!$R$2:$R$73)-SUM(Data_Raw!$I$2:$I$73) -> 1.818612 | E10: =E9+D10 -> 8194.9182 | F10: Controllable Opex | G10: Favorable headcount replacement timing and open req lag
B11: Marketing Spend Optimization | C11: 0 | D11: =SUM(Data_Raw!$S$2:$S$73)-SUM(Data_Raw!$J$2:$J$73) -> 47.73728 | E11: =E10+D11 -> 8242.6555 | F11: Controllable Opex | G11: Pruned lower-ROI performance acquisition channels
B12: Technology & Cloud Efficiencies | C12: 0 | D12: =SUM(Data_Raw!$T$2:$T$73)-SUM(Data_Raw!$K$2:$K$73) -> 11.862777 | E12: =E11+D12 -> 8254.5183 | F12: Fixed Opex | G12: Consolidation of multi-region cloud instances & license true-ups
B13: Facilities & G&A Variances | C13: 0 | D13: =SUM(Data_Raw!$U$2:$U$73)-SUM(Data_Raw!$L$2:$L$73) -> -6.2365985 | E13: =E12+D13 -> 8248.2817 | F13: Fixed Opex | G13: Disciplined travel and discretionary administrative controls
B14: Reconciled Actual EBIT Result | C14: 0 | D14: 0 | E14: =E13 -> 8248.2817 | F14: Actuals | G14: Final operating profitability matching management financials

Sheet Dashboard
B2: Executive Management Dashboard | I2: INTEGRITY AUDIT
B3: Consolidated performance, KPI scorecard, and segment profitability. | I3: =IF(Checks!$C$13="ALL CHECKS PASS", "🟢 ALL CHECKS PASS", "🔴 AUDIT WARNING") -> 🟢 ALL CHECKS PASS
B5: TOTAL REVENUE | D5: OPERATING EBIT | F5: EBIT MARGIN | H5: OPEX RATIO
B6: =Monthly_Report!D30 -> 27609.673 | D6: =Monthly_Report!H30 -> 8248.2817 | F6: =Monthly_Report!L30 -> 0.29874608 | H6: =(Monthly_Report!D30-Monthly_Report!H30)/Monthly_Report!D30 -> 0.70125392
B7: ="vs Plan: " & TEXT(Monthly_Report!F30, "+#,##0.0;-#,##0.0") & " (" & TEXT(Monthly_Report!G30, "+0.0%;-0.0%") & ")" -> vs Plan: -628.6 (-2.2%) | D7: ="vs Plan: " & TEXT(Monthly_Report!J30, "+#,##0.0;-#,##0.0") & " (" & TEXT(Monthly_Report!K30, "+0.0%;-0.0%") & ")" -> vs Plan: -377.6 (-4.4%) | F7: ="Target: " & TEXT(Monthly_Report!I30/Monthly_Report!E30, "0.0%") -> Target: 30.5% | H7: ="Plan: " & TEXT((Monthly_Report!E30-Monthly_Report!I30)/Monthly_Report!E30, "0.0%") -> Plan: 69.5%
B10: BUSINESS UNIT PERFORMANCE & MARGIN CONTRIBUTION
B11: Segment | C11: Actual Rev | D11: Budget Rev | E11: Rev Var ($) | F11: Rev Var (%) | G11: Actual EBIT | H11: Budget EBIT | I11: EBIT Var ($) | J11: EBIT Margin
B12: Consumer | C12: =SUMIFS(Data_Raw!$E$2:$E$73, Data_Raw!$D$2:$D$73, "Consumer") -> 14158.336 | D12: =SUMIFS(Data_Raw!$O$2:$O$73, Data_Raw!$D$2:$D$73, "Consumer") -> 14477.651 | E12: =C12-D12 -> -319.31575 | F12: =E12/D12 -> -0.02205577 | G12: =SUMIFS(Data_Raw!$AE$2:$AE$73, Data_Raw!$D$2:$D$73, "Consumer") -> 3382.1665 | H12: =SUMIFS(Data_Raw!$AG$2:$AG$73, Data_Raw!$D$2:$D$73, "Consumer") -> 3522.3334 | I12: =G12-H12 -> -140.1669 | J12: =G12/C12 -> 0.23888165
B13: Digital | C13: =SUMIFS(Data_Raw!$E$2:$E$73, Data_Raw!$D$2:$D$73, "Digital") -> 5141.5675 | D13: =SUMIFS(Data_Raw!$O$2:$O$73, Data_Raw!$D$2:$D$73, "Digital") -> 5258.5279 | E13: =C13-D13 -> -116.9604 | F13: =E13/D13 -> -0.022242042 | G13: =SUMIFS(Data_Raw!$AE$2:$AE$73, Data_Raw!$D$2:$D$73, "Digital") -> 2215.8052 | H13: =SUMIFS(Data_Raw!$AG$2:$AG$73, Data_Raw!$D$2:$D$73, "Digital") -> 2346.5402 | I13: =G13-H13 -> -130.73502 | J13: =G13/C13 -> 0.43095907
B14: Enterprise | C14: =SUMIFS(Data_Raw!$E$2:$E$73, Data_Raw!$D$2:$D$73, "Enterprise") -> 8309.7704 | D14: =SUMIFS(Data_Raw!$O$2:$O$73, Data_Raw!$D$2:$D$73, "Enterprise") -> 8502.1141 | E14: =C14-D14 -> -192.3437 | F14: =E14/D14 -> -0.022623044 | G14: =SUMIFS(Data_Raw!$AE$2:$AE$73, Data_Raw!$D$2:$D$73, "Enterprise") -> 2650.31 | H14: =SUMIFS(Data_Raw!$AG$2:$AG$73, Data_Raw!$D$2:$D$73, "Enterprise") -> 2756.9804 | I14: =G14-H14 -> -106.67041 | J14: =G14/C14 -> 0.31893902
B15: Consolidated Total | C15: =SUM(C12:C14) -> 27609.673 | D15: =SUM(D12:D14) -> 28238.293 | E15: =C15-D15 -> -628.61985 | F15: =E15/D15 -> -0.022261255 | G15: =SUM(G12:G14) -> 8248.2817 | H15: =SUM(H12:H14) -> 8625.854 | I15: =G15-H15 -> -377.57233 | J15: =G15/C15 -> 0.29874608
B17: EXECUTIVE DECISION-SUPPORT & COMMENTARY
B18: P&L Focus Area | C18: Observed Variance | D18: Driver Isolation | E18: Actionable Management Recommendation
B19: Top-line Performance | C19: Consolidated Revenue is ₹-628.6m (-2.3%) below plan | D19: Enterprise contract renewal deferrals and price concession pressure | E19: Accelerate Q4 enterprise pipeline conversion; enforce strict discounting governance.
B20: Operating Profitability | C20: Operating EBIT is ₹-377.6m (-4.4%) adverse to budget | D20: Top-line volume drop amplified by Consumer commodity cost inflation | E20: Institute temporary hiring freezes on back-office roles; reprioritize discretionary SG&A.
B21: Digital Business Unit | C21: Digital segment delivered highest margin contribution (43.1%) | D21: High-margin subscription scale and favorable gross revenue retention | E21: Reallocate growth capex from underperforming Consumer SKUs into Digital expansion.

Sheet KPI_Tree
B2: FP&A Strategic KPI & Value Driver Architecture | I2: INTEGRITY AUDIT
B3: Hierarchical operational levers directly connecting unit economics to return on capital. | I3: =IF(Checks!$C$13="ALL CHECKS PASS", "🟢 ALL CHECKS PASS", "🔴 AUDIT WARNING") -> 🟢 ALL CHECKS PASS
B5: ENTERPRISE DUPONT / VALUE DRIVER FRAMEWORK
B6: Strategic Tier | C6: Primary KPI Metric | D6: Operational Formula / Logic | E6: Functional Owner | F6: Management Action Lever
B7: Tier 1: Shareholder Value | C7: Return on Invested Capital (ROIC) | D7: NOPAT / (Total Debt + Equity − Cash) | E7: CFO / Board | F7: Capital allocation, hurdle rates & share buybacks
B8: Tier 2: Core Profitability | C8: Operating EBIT Margin (%) | D8: EBIT / Consolidated Net Revenue | E8: Business Unit Heads | F8: Pricing power, product mix & cost discipline
B9: Tier 2: Capital Efficiency | C9: Cash Conversion Cycle (CCC) | D9: Days Sales Outstanding + DIO − DPO | E9: Treasury & Operations | F9: Working capital terms, DSO collection enforcement
B10: Tier 3: Commercial Engine | C10: Revenue Volume & ASP | D10: Contract Units × Realized Price / Mix | E10: Chief Commercial Officer | F10: Discount thresholds, bundling & win-rate governance
B11: Tier 3: Manufacturing / Supply | C11: Gross Profit Margin (%) | D11: (Revenue − COGS) / Revenue | E11: Head of Supply Chain | F11: Vendor procurement, direct labor yield & logistics
B12: Tier 3: Workforce Efficiency | C12: Revenue per Headcount (₹m) | D12: Consolidated Revenue / Total FTEs | E12: CHRO & Business Heads | F12: Span of control, automation & org productivity
B13: Tier 4: Opex Efficiency | C13: Marketing CAC / Payback | D13: Acquisition Spend / Net New Customers | E13: Chief Marketing Officer | F13: Channel attribution & customer lifetime value (LTV)
B14: Tier 4: Technology ROI | C14: Cloud Infrastructure / Rev | D14: Total Hosting & SaaS / Net Revenue | E14: Chief Technology Officer | F14: Instance right-sizing, auto-scaling & license audits

Sheet Checks
B2: Model Financial Integrity & Audit Controls | G2: INTEGRITY AUDIT
B3: Continuous automated validation guaranteeing zero reconciliation discrepancies. | G3: =IF(Checks!$C$13="ALL CHECKS PASS", "🟢 ALL CHECKS PASS", "🔴 AUDIT WARNING") -> 🟢 ALL CHECKS PASS
B5: AUTOMATED RECONCILIATION CONTROLS
B6: Audit Control Test Description | C6: Model Formula Source | D6: Discrepancy | E6: Tolerance | F6: Audit Status | G6: Resolution Guidance
B7: Revenue Tie-Out: Dashboard Segment Total vs Monthly Total | C7: Dynamic Link | D7: =Dashboard!C15-Monthly_Report!D30 -> 0 | E7: 0.01 | F7: =IF(ABS(D7)<=E7, "PASS", "FLAGGED") -> PASS | G7: Dashboard must reconcile with monthly reporting roll-forward
B8: EBIT Tie-Out: Dashboard Segment Total vs Monthly Total | C8: Dynamic Link | D8: =Dashboard!G15-Monthly_Report!H30 -> 0 | E8: 0.01 | F8: =IF(ABS(D8)<=E8, "PASS", "FLAGGED") -> PASS | G8: Segment operating profits must tie to corporate P&L
B9: P&L Bridge Tie-Out: Driver Reconciled EBIT vs Actual EBIT | C9: Dynamic Link | D9: =Driver_Analysis!E14-Monthly_Report!H30 -> 0 | E9: 0.01 | F9: =IF(ABS(D9)<=E9, "PASS", "FLAGGED") -> PASS | G9: Decomposed variance bridge must match final actual EBIT exactly
B10: Database Completeness: Raw Row Count Audit | C10: Dynamic Link | D10: =COUNT(Data_Raw!E2:E73)-72 -> 0 | E10: 0.01 | F10: =IF(ABS(D10)<=E10, "PASS", "FLAGGED") -> PASS | G10: Ensures all 24 months and 3 segments are populated
B13: MASTER AUDIT SUMMARY: | C13: =IF(COUNTIF(F7:F10, "FLAGGED")=0, "ALL CHECKS PASS", "ATTENTION: AUDIT FAILED") -> ALL CHECKS PASS
